mgpu/__init__.py
mgpu/core.py
mgpu/models.py
mgpu/utils.py
mgpu/validators.py
mgpu-0.3.0.dist-info/LICENSE
mgpu-0.3.0.dist-info/METADATA
mgpu-0.3.0.dist-info/WHEEL
mgpu-0.3.0.dist-info/RECORD
