Metadata-Version: 2.1
Name: mgpu
Version: 0.3.0
Summary: 
Home-page: https://github.com/roycek7/mgpu
License: MIT
Author: Pritish Roy
Requires-Python: >=3.9,<4.0
Classifier: License :: OSI Approved :: MIT License
Classifier: Programming Language :: Python :: 3
Classifier: Programming Language :: Python :: 3.9
Classifier: Programming Language :: Python :: 3.10
Classifier: Programming Language :: Python :: 3.11
Requires-Dist: pydantic (>=2.10.2,<3.0.0)
Requires-Dist: vllm (>=0.6.4.post1,<0.7.0)
Project-URL: Repository, https://github.com/roycek7/mgpu
